drf_toolmux/__init__.py
drf_toolmux/bot.py
drf_toolmux/distance.py
drf_toolmux/exception.py
drf_toolmux/pagination.py
drf_toolmux/responses.py
drf_toolmux/translate.py
drf_toolmux-0.1.3.dist-info/METADATA
drf_toolmux-0.1.3.dist-info/WHEEL
drf_toolmux-0.1.3.dist-info/top_level.txt
drf_toolmux-0.1.3.dist-info/RECORD
