Metadata-Version: 2.1
Name: drf-toolmux
Version: 0.1.3
Summary: Django Rest Framework collected classes for Mirmux
Home-page: https://github.com/me/myproject
Author: Mirmux
Author-email: mirfayziyev5@gmail.com
License: MIT
Platform: UNKNOWN
Classifier: License :: OSI Approved :: MIT License
Classifier: Programming Language :: Python
Classifier: Programming Language :: Python :: 3
Classifier: Programming Language :: Python :: 3.6
Classifier: Programming Language :: Python :: Implementation :: CPython
Classifier: Programming Language :: Python :: Implementation :: PyPy
Requires-Python: >=3.8.0
Requires-Dist: Django (>=4.0)
Requires-Dist: djangorestframework (>=3.0)
Requires-Dist: pyTelegramBotAPI (==4.20)
